src/tensor_product_binding/__init__.py
src/tensor_product_binding/binding_implementations.py
src/tensor_product_binding/compositional_semantics.py
src/tensor_product_binding/compositional_semantics_modular.py
src/tensor_product_binding/neural_binding.py
src/tensor_product_binding/smolensky_tpr_implementation.py
src/tensor_product_binding/symbolic_structures.py
src/tensor_product_binding/tensor_product_binding.py
src/tensor_product_binding/tensor_product_binding_core.py
src/tensor_product_binding/test_modularization.py
src/tensor_product_binding/tpr_comprehensive_config.py
src/tensor_product_binding/compositional_modules/__init__.py
src/tensor_product_binding/compositional_modules/advanced_composition.py
src/tensor_product_binding/compositional_modules/semantic_engine.py
src/tensor_product_binding/compositional_modules/semantic_structures.py
src/tensor_product_binding/compositional_modules/utilities.py
src/tensor_product_binding/config/__init__.py
src/tensor_product_binding/config/config_classes.py
src/tensor_product_binding/config/defaults.py
src/tensor_product_binding/config/enums.py
src/tensor_product_binding/core/__init__.py
src/tensor_product_binding/core/algorithms.py
src/tensor_product_binding/core/binding_operations.py
src/tensor_product_binding/core/vector_spaces.py
src/tensor_product_binding/neural_binding_modules/__init__.py
src/tensor_product_binding/neural_binding_modules/abstract_base.py
src/tensor_product_binding/neural_binding_modules/configuration.py
src/tensor_product_binding/neural_binding_modules/numpy_implementation.py
src/tensor_product_binding/neural_binding_modules/pytorch_implementation.py
src/tensor_product_binding/neural_modules/__init__.py
src/tensor_product_binding/neural_modules/base_network.py
src/tensor_product_binding/neural_modules/complete_neural_implementations.py
src/tensor_product_binding/neural_modules/configurations.py
src/tensor_product_binding/neural_modules/numpy_network.py
tensor_product_binding-1.4.0.dist-info/METADATA
tensor_product_binding-1.4.0.dist-info/WHEEL
tensor_product_binding-1.4.0.dist-info/licenses/LICENSE
tensor_product_binding-1.4.0.dist-info/RECORD
