Metadata-Version: 2.4
Name: tensor-product-binding
Version: 1.4.0
Summary: Structured knowledge representation in neural networks via tensor products
Project-URL: Funding, https://www.paypal.com/cgi-bin/webscr?cmd=_s-xclick&hosted_button_id=WXQKYYKPHWXHS
Project-URL: Sponsor, https://github.com/sponsors/benedictchen
Author-email: Benedict Chen <benedict@benedictchen.com>
Maintainer-email: Benedict Chen <benedict@benedictchen.com>
License: Custom Non-Commercial License with Donation Requirements
License-File: LICENSE
Requires-Python: >=3.9
Requires-Dist: matplotlib>=3.5.0
Requires-Dist: numpy>=1.21.0
Requires-Dist: scikit-learn>=1.0.0
Requires-Dist: scipy>=1.7.0
Provides-Extra: test
Requires-Dist: pytest-cov>=4.0; extra == 'test'
Requires-Dist: pytest>=7.0; extra == 'test'
